pyMDReport/Report.py
pyMDReport/__init__.py
pyMDReport/exceptions.py
pyMDReport/types.py
pyMDReport/Components/Anchor.py
pyMDReport/Components/ComposedText.py
pyMDReport/Components/Group.py
pyMDReport/Components/Heading.py
pyMDReport/Components/Link.py
pyMDReport/Components/Quote.py
pyMDReport/Components/Text.py
pyMDReport/Components/pyMDComponent.py
pymdreport-0.0.2.dist-info/METADATA
pymdreport-0.0.2.dist-info/WHEEL
pymdreport-0.0.2.dist-info/licenses/LICENSE
pymdreport-0.0.2.dist-info/RECORD
